oemof_industry/emission_constraint.py
oemof_industry/mimo_converter.py
oemof_industry-0.1.0.dist-info/METADATA
oemof_industry-0.1.0.dist-info/WHEEL
oemof_industry-0.1.0.dist-info/RECORD
