Metadata-Version: 2.1
Name: oemof-industry
Version: 0.1.0
Summary: 
Author: Hendrik Huyskens
Author-email: hendrik.huyskens@rl-institut.de
Requires-Python: >=3.9
Classifier: Programming Language :: Python :: 3
Classifier: Programming Language :: Python :: 3.9
Classifier: Programming Language :: Python :: 3.10
Classifier: Programming Language :: Python :: 3.11
Classifier: Programming Language :: Python :: 3.12
